{
  "Update": "Atualização disponível! Clique aqui para iniciá-la.",
  "Header_ChooseLanguage": "Escolha o Idioma:",
  "Steam_ShowSteamID": "SteamID",
  "Steam_ShowVac": "Status de VAC",
  "Steam_ShowLastLogin": "Última hora de login",
  "Steam_ShowLimited": "Status Limitado",
  "Steam_ShowAccUsername": "Nome de usuário da conta",
  "Steam_ShowMiniProfile": "Mini perfil (passe o mouse sobre o avatar)",
  "Steam_ShowAvatarFrame": "Sobreposição da moldura do avatar",
  "Tooltip_SteamShowMiniProfile": "Buscar o HTML do mini perfil da Steam em segundo plano e mostrá-lo após passar o mouse sobre o avatar da conta por um segundo.",
  "Tooltip_SteamShowAvatarFrame": "Baixar a moldura do avatar equipada da página do mini perfil e desenhá-la sobre a imagem de perfil.",
  "Steam_Tray_AccountName": "Mostrar nome da conta [não o nome de amigo]",
  "Steam_CheckVac": "Verificar status do VAC da conta",
  "Steam_OverrideDefaultState": "Substituir estado padrão de login:",
  "Steam_StartSilent": "Abrir Steam na bandeja ao alternar (iniciar Steam com '-silent')",
  "Steam_OldUi": "Use a interface antiga da Steam (-vgui)",
  "Button_AddNew": "Adicionar Novo",
  "Button_SaveCurrent": "Salvar atual",
  "Button_Cancel": "Cancelar",
  "Button_Always": "Sempre",
  "Button_Login": "Entrar",
  "Button_Launch": "Iniciar",
  "Tooltip_Login": "Entrar com a conta selecionada",
  "Tooltip_AddNew": "Limpar a sessão e entrar com uma nova conta",
  "Tooltip_SaveCurrent": "Salvar a sessão atual como uma conta nomeada",
  "Tooltip_Launch": "Iniciar a plataforma sem alternar contas",
  "Tooltip_LaunchAfterSwitch": "Iniciar a plataforma após alternar para a conta {name}",
  "Tooltip_LaunchAfterSwitch_NameFallback": "a conta selecionada",
  "Toast_AccountSaved": "Conta salva.",
  "Toast_AccountSwitched": "Conta alternada.",
  "Toast_SwitchFailed": "Não foi possível alternar a conta.",
  "Toast_SaveFailed": "Não foi possível salvar a sessão atual.",
  "Toast_StatsReportFailed": "Não foi possível carregar o relatório de estatísticas.",
  "Toast_LaunchFailed": "Não foi possível iniciar.",
  "Modal_SaveCurrent_Title": "Salvar sessão atual",
  "Modal_SaveCurrent_Body": "Digite um nome de exibição para esta conta:",
  "Button_Close": "Fechar",
  "Button_RefreshImages": "Atualizar imagens",
  "Button_RefreshProfileImages": "Atualizar imagens de perfil",
  "Button_ClearCachedProfileImages": "Limpar imagens de perfil em cache",
  "Button_ResetSettings": "Redefinir configurações",
  "Button_AdvancedCleaning": "Limpeza avançada...",
  "Button_ClearLog": "Limpar registros",
  "Button_WikiInfo": "Mais informações (Wiki)",
  "Button_ManagePlatforms": "Gerenciar Plataformas",
  "Button_Backup": "Backup",
  "Button_BackupAll": "Fazer backup de tudo",
  "Button_Restore": "Restaurar",
  "Button_OpenBackup": "Abrir pasta de backup",
  "Button_Back": "Voltar",
  "Button_LocatePlatformsJson": "Localizar Platforms.json…",
  "Button_RestoreBundledPlatforms": "Restaurar lista padrão",
  "Settings_SteamCollectInfo": "Colete a foto do perfil do Steam e o status do VAC do Steam",
  "Settings_Shortcut": "{platform} Atalho do Switcher Desktop",
  "Settings_Admin": "Executar {platform} como Admin",
  "Settings_ImageExpiry": "Dias para as fotos de perfil expirarem:",
  "Settings_SteamAPIKey": "Chave da API da Web do Steam (opcional)",
  "Settings_SteamAPIKey_Note": "Definir uma chave de API fará com que o indicador Limitado (borda amarela) seja exibido para contas que são Banidas da Comunidade.",
  "Settings_Header_AppWide": "Configurações em todo o aplicativo",
  "Settings_Header_GeneralSettings": "Configurações gerais",
  "Settings_Header_AccountDisplay": "Configurações de exibição da conta",
  "Settings_Header_ExtraPlatforms": "Configurações da plataforma",
  "Settings_Header_GeneralTools": "Ferramentas Gerais",
  "Settings_Header_OtherTools": "Outras Ferramentas",
  "Settings_Header_TraySettings": "Configurações da bandeja",
  "Settings_Header_ProfileImages": "Imagens de perfil",
  "Settings_ProfileImageExpiryDays": "Baixar novamente as imagens de perfil após (dias):",
  "Settings_PullAccountImages": "Obter imagens de conta de arquivos",
  "Settings_Header_BackupRestore": "Configurações da plataforma de backup e restauração",
  "Settings_Header_Language": "Idioma",
  "Settings_Header_System": "Sistema",
  "Settings_Header_Theme": "Tema",
  "Settings_Header_Program": "Programa",
  "Settings_Header_StatsSharing": "Estatísticas e compartilhamento",
  "Settings_Header_Platform": "{platformName} configurações",
  "Settings_Header_LaunchOptions": "Opções de inicialização",
  "Settings_LaunchArgumentsForPlatform": "Argumentos de inicialização para {platform}",
  "Settings_LaunchArguments_Hint": "Opções extras opcionais de linha de comando para inicialização. Por exemplo: '-dev' ou '-novid'.",
  "Settings_Header_ProcessManagement": "Gerenciamento de processos",
  "Settings_ForgetAccountEnabled": "Esquecer conta",
  "Settings_ResetConfirm": "Redefinir todas as configurações de {platform} para os padrões?",
  "Toast_SettingsReset": "As configurações foram redefinidas.",
  "Toast_PlatformPathUpdated": "O caminho do executável da plataforma foi atualizado.",
  "Toast_ImagesRefreshing": "As imagens de perfil estão sendo atualizadas.",
  "Toast_ProfileImagesCleared": "Imagens de perfil apagadas.",
  "Toast_AccountTagsCleared": "Tags de conta apagadas.",
  "Toast_TaggedVisibleAccounts": "{count} conta(s) visível(is) marcadas com {tag}.",
  "Toast_NoVisibleAccounts": "Nenhuma conta visível.",
  "Settings_TrayMax": "Número máximo de contas a serem lembradas:",
  "Settings_ExtraPlatformsDisabled": "Plataformas desativadas. Clique para habilitá-las.",
  "Settings_ExtraPlatformsEnabled": "Plataformas visíveis. Clique para desativá-las.",
  "Settings_CollectStats": "Coletar estatísticas",
  "Settings_CrashReportAutoSubmit": "Enviar automaticamente relatórios de falhas",
  "Settings_ShareStats": "Compartilhe estatísticas anonimamente (recomendado)",
  "Settings_DiscordRpc": "Discord Rich Presence (RPC)",
  "Settings_DiscordRpcShare": "Compartilhar total de mudanças",
  "Settings_ViewStats": "Visualizar estatísticas",
  "Settings_SuggestFeature": "Sugerir funcionalidade/alteração",
  "Settings_PrereleaseUpdates": "Atualizações de pré-lançamento",
  "Preview": "Pré-visualizar",
  "Settings_ClearStats": "Redefinir",
  "Settings_CurrentLocation": "Local de instalação atual: {path}",
  "Settings_CurrentDataLocation": "Localização atual dos dados do usuário: {path}",
  "Settings_SetDataLocation": "[Definir local de dados de usuário personalizado]",
  "Settings_OpenUserDataFolder": "[Abrir Pasta]",
  "Settings_Header_Security": "Segurança",
  "Security_SetAppPassword": "Definir senha do aplicativo",
  "Security_RemoveAppPassword": "Remover senha do aplicativo",
  "Security_EncryptSavedAccountData": "Criptografar dados de conta salvos/em cache",
  "Security_SetPasswordIntro": "Esta senha é necessária para abrir e acessar o aplicativo.",
  "Security_SetPasswordEncryptionHint": "Ela não criptografa dados de conta salvos/em cache sozinha. Para criptografar dados de conta salvos/em cache, ative a caixa de seleção nas configurações depois de definir esta senha.",
  "Security_Password": "Senha",
  "Security_ConfirmPassword": "Confirmar senha",
  "Security_SetPasswordMismatch": "As senhas não correspondem.",
  "Security_CurrentPasswordBody": "Insira sua senha atual do aplicativo para continuar.",
  "Security_RemovePasswordEncryptedBody": "Insira sua senha atual do aplicativo. Dados de conta salvos/em cache criptografados serão descriptografados antes que a senha seja removida.",
  "Security_EnableEncryption": "Ativar criptografia de dados salvos",
  "Security_EnableEncryptionBody": "Insira sua senha atual do aplicativo para criptografar dados de conta salvos/em cache.",
  "Security_DisableEncryption": "Desativar criptografia de dados salvos",
  "Security_DisableEncryptionBody": "Insira sua senha atual do aplicativo para descriptografar dados de conta salvos/em cache.",
  "Security_WeakPasswordTitle": "Senha fraca",
  "Security_WeakPasswordBody": "Esta senha pode ser fácil de adivinhar. Você pode continuar, mas a força da criptografia depende desta senha.",
  "Security_WeakPasswordContinue": "Continuar",
  "Security_AppPasswordSet": "Senha do aplicativo definida.",
  "Security_AppPasswordRemoved": "Senha do aplicativo removida.",
  "Security_EncryptionEnabled": "Criptografia de dados de conta salvos/em cache ativada.",
  "Security_EncryptionDisabled": "Criptografia de dados de conta salvos/em cache desativada.",
  "Security_PasswordActionFailed": "Ação de segurança falhou.",
  "Security_InterruptedRestorePending": "Uma restauração de conta anterior foi interrompida. Repare o estado temporário de restauração e, se necessário, alterne novamente para a conta desejada.",
  "Security_InterruptedRestore_Title": "Restauração de conta interrompida",
  "Security_InterruptedRestore_Body": "Uma restauração de conta anterior foi interrompida antes do fechamento do aplicativo. O reparo recomendado limpa o estado temporário de restauração e marca a restauração interrompida como tratada. Após o reparo, alterne novamente para a conta desejada se a plataforma não estiver na conta esperada.",
  "Security_InterruptedRestore_Affected": "Diário(s) de restauração afetado(s):",
  "Security_InterruptedRestore_Repair": "Reparar agora",
  "Security_InterruptedRestore_Later": "Depois",
  "Security_InterruptedRestore_Repaired": "Estado de restauração interrompida reparado.",
  "Security_InterruptedRestore_RepairFailed": "Falha ao reparar restauração interrompida.",
  "Security_QuarantineStatus": "{count} quarentena(s) de conta criptografada precisam de atenção.",
  "Security_QuarantineRetry": "Tentar importar novamente",
  "Security_QuarantineRetryBody": "Insira a senha antiga do aplicativo para esta quarentena. Blobs válidos serão importados de volta para os dados de conta salvos em texto claro.",
  "Security_QuarantineRetryDone": "Importação da quarentena concluída.",
  "Security_QuarantineDelete": "Excluir quarentena",
  "Security_QuarantineDeleteBody": "Isso exclui permanentemente os blobs criptografados em quarentena e seus materiais de recuperação.",
  "Security_Locked_Title": "Aplicativo bloqueado",
  "Security_Locked_Body": "Insira sua senha do aplicativo para acessar as contas.",
  "Security_Unlock": "Desbloquear",
  "Security_UnlockFailed": "Senha do aplicativo inválida.",
  "Security_Progress_Title": "Operação de segurança em andamento",
  "Security_Progress_Working": "Trabalhando...",
  "Security_Progress_Encrypt": "Criptografando dados de conta salvos/em cache...",
  "Security_Progress_Decrypt": "Descriptografando dados de conta salvos/em cache...",
  "Security_Progress_RemovePassword": "Removendo senha do aplicativo...",
  "Security_Progress_RetryQuarantine": "Importando dados de conta em quarentena...",
  "Security_Progress_RepairInterruptedRestore": "Reparando estado de restauração interrompida...",
  "Security_AccountDataBroken": "Dados salvos indisponíveis",
  "Settings_PickFolder": "Escolher pasta de {platform}",
  "Settings_OpenFolder": "Abrir pasta de {platform}",
  "Settings_StreamerMode": "Ativar modo streamer",
  "Settings_ExitToTray": "Sair minimiza para a bandeja",
  "Settings_DesktopShortcut": "Atalho da área de trabalho",
  "Settings_Tray_StartWindows": "Iniciar Bandeja com o Windows",
  "Settings_CurrentStyle": "Estilo Atual",
  "Settings_AccentColor": "Cor de destaque",
  "Settings_AccentColor_Custom": "Personalizado",
  "Settings_AccentColor_CustomPicker": "Destaque personalizado",
  "Settings_ClearBackground": "Limpar plano de fundo",
  "Settings_ResetToThemeBackground": "Redefinir para o plano de fundo do tema",
  "Settings_ClearPlatformBackground": "Limpar plano de fundo da plataforma",
  "Settings_BgOpacity": "Opacidade",
  "Settings_BgBlur": "Desfoque",
  "Settings_BgAlignAria": "Alinhamento do plano de fundo",
  "Settings_BgFitAria": "Modo de preenchimento do plano de fundo",
  "Settings_BgAlign_Center": "Centro",
  "Settings_BgAlign_Left": "Esquerda",
  "Settings_BgAlign_Right": "Direita",
  "Settings_BgAlign_Top": "Topo",
  "Settings_BgAlign_Bottom": "Base",
  "Settings_BgFit_Cover": "Cobrir",
  "Settings_BgFit_Contain": "Ajustar",
  "Settings_BgFit_Fill": "Preencher",
  "Settings_BgFit_None": "Tamanho real",
  "Settings_BgFit_ScaleDown": "Reduzir",
  "DropZone_SetAppBg": "Definir plano de fundo do aplicativo",
  "DropZone_SetPlatformBg": "Definir plano de fundo de {platform}",
  "Toast_AppBgSet": "Plano de fundo do aplicativo atualizado.",
  "Toast_PlatformBgSet": "Plano de fundo de {platform} atualizado.",
  "Settings_Protocol": "Ativar protocolo tcno:\\\\ (recomendado)",
  "Settings_StartCentered": "Iniciar programa centralizado",
  "Settings_AnimationsEnabled": "Habilitar animações",
  "Settings_ControllerSupport": "Suporte a controle",
  "Settings_CommandPaletteHotkey": "Atalho da paleta de comandos",
  "Settings_CommandPaletteHotkey_Prompt": "Pressione o atalho...",
  "Settings_OfflineMode": "Modo offline (sem atividade de rede)",
  "Settings_WindowsAccent": "Acento do Windows",
  "Settings_HelpTranslate": "[Ajuda a traduzir]",
  "Settings_ViewTranslators": "[Créditos]",
  "Settings_Header_ActiveBrowser": "(Avançado) Definir mecanismo de renderização:",
  "Settings_Header_ClosingMethod": "(Avançado) Definir método para fechar {platform}",
  "Settings_Header_StartingMethod": "(Avançado) Definir método para iniciar {platform}",
  "Settings_AutoStart": "Iniciar automaticamente {platform} na troca de conta",
  "Settings_ShowSteamSwitcher": "Mostrar o trocador de contas do Steam (NÃO use isso, ou pode quebrar o TcNo Account Switcher)",
  "Settings_NoPlatforms": "No momento, não há plataformas habilitadas. Marque as plataformas opcionais abaixo para habilitá-las ou desmarque as plataformas desabilitadas.",
  "Settings_MinimizeOnSwitch": "Minimizar o alternador ao trocar de conta",
  "Settings_ShowShortNotes": "Prévia da nota abaixo do nome de usuário",
  "Settings_ShowLastUsed": "Mostrar horário do último uso nos blocos de conta",
  "Filter_Menu": "Filtrar e ordenar",
  "Filter_Search": "Pesquisar",
  "Filter_SortBy": "Ordenar por",
  "Filter_Sort_AZ": "A a Z",
  "Filter_Sort_ZA": "Z a A",
  "Filter_Sort_Username": "Nome de usuário",
  "Filter_Sort_LastUsed": "Último uso",
  "Filter_Sort_NewOld": "Novo a Antigo",
  "Filter_Sort_OldNew": "Antigo a Novo",
  "Search_Section_Platform": "PLATAFORMA",
  "Search_Section_DisabledPlatform": "DESATIVADO",
  "Search_Section_Account": "CONTA",
  "Search_Section_Game": "APLICATIVO",
  "Search_Section_Command": "COMANDO",
  "Search_Hint_EnablePlatform": "Clique para habilitar a plataforma",
  "Search_Hint_Games": "Aplicativo/Jogos",
  "Command_SearchPlaceholder": "> Digite um comando",
  "Command_OpenSettings": "Abrir configurações",
  "Command_ManagePlatforms": "Gerenciar plataformas",
  "Command_CheckForUpdates": "Verificar atualizações",
  "Command_SuggestFeature": "Sugerir uma funcionalidade",
  "Command_LoginSelected": "Entrar na conta selecionada",
  "Command_AddNewAccount": "Adicionar nova conta",
  "Command_SaveCurrentAccount": "Salvar conta atual",
  "Command_RefreshAccounts": "Atualizar contas",
  "Command_ClearAccountTags": "Limpar tags de conta",
  "Command_ClearAccountTagsConfirm": "Remover todas as tags de cada conta {platform}?",
  "Command_TagVisibleAccounts": "Marcar todas as contas visíveis",
  "Command_TagVisibleAccountsPrompt": "Insira uma tag para aplicar a {count} conta(s) visível(is). Tags existentes serão reutilizadas.",
  "Command_ClearAllImages": "Limpar todas as imagens de perfil",
  "Command_ClearAllImagesConfirm": "Limpar imagens de perfil em cache de cada conta {platform}?",
  "Command_RefreshAllImages": "Atualizar todas as imagens de perfil",
  "Command_OpenPlatformSettings": "Abrir configurações de {platform}",
  "Command_GoHome": "Ir para início",
  "PreviewCss": "Visualizar CSS",
  "Settings_PreviewCss": "Esta é a página de visualização CSS. Você pode visualizar alguns elementos que aparecem no programa e ver como eles se parecem com o seu tema. Esta página é útil para quem cria temas!",
  "Settings_PreviewCssHeader": "Página de visualização do CSS",
  "Stats_Disabled": "A coleção de estatísticas está desativada.",
  "Stats_InDepth": "Análise detalhada de estatísticas",
  "Stats_ModalShareEnabled": "Estas estatísticas são compartilhadas anonimamente e estão incluídas nos totais públicos.",
  "Stats_ModalShareDisabled": "Estas estatísticas NÃO são compartilhadas anonimamente e NÃO estão incluídas nos totais públicos.",
  "Stats_OperatingSystem": "Sistema operacional: ",
  "Stats_FirstLaunch": "Primeiro lançamento: ",
  "Stats_LaunchCount": "Contagem de inicialização: ",
  "Stats_CrashCount": "Contagem de falhas: ",
  "Stats_MostUsedPlatform": "Plataforma mais utilizada: ",
  "Stats_TotalTime": "Tempo total gasto no aplicativo: ",
  "Stats_TotalSwitches": "Total de trocas de conta: ",
  "Stats_TotalGamesLaunched": "Total de aplicativos/jogos lançados via switcher: ",
  "Stats_UniqueDaysLong": "Dias únicos com contas trocadas: ",
  "Stats_LastUpload": "Último Upload: ",
  "Stats_SwitcherStats": "Estatísticas do mudador de conta: ",
  "Stats_PageStats": "Estatísticas da página: ",
  "Stats_VisitsTotalTime": "{visits} total de visitas, {hours} tempo total",
  "Stats_Accounts": "Contas: ",
  "Stats_Switches": "Trocas: ",
  "Stats_FirstActive": "Primeiro ativo: ",
  "Stats_LastActive": "Último ativo: ",
  "Stats_UniqueDays": "Dias únicos: ",
  "Stats_GameShortcuts": "Atalhos do jogo: ",
  "Stats_GameShortcutsHotbar": "Atalhos do jogo (na barra de atalho): ",
  "Stats_GamesLaunched": "Jogos lançados: ",
  "Stats_Tags": "Marcadores:",
  "Stats_TaggedAccounts": "Contas marcadas:",
  "Stats_TotalTags": "Total de marcadores:",
  "Stats_TotalTaggedAccounts": "Total de contas marcadas:",
  "Stats_MetricsToShow": "Métricas exibidas:",
  "Stats_MetricsProvidedBy": "Dados de métricas fornecidos por:",
  "Stats_MetricsAffiliationNote": "NOTA: Este programa não é afiliado ou endossado por este site ou serviço.",
  "Locked": "Bloqueado",
  "Cleaning_Header_General": "Limpeza Geral",
  "Cleaning_Header_LoginHistory": "Limpar meu histórico de login",
  "Cleaning_ImportantInfoHeader": "Informações importantes:",
  "Cleaning_ImportantInfo": "Clicar em um botão excluirá o (s) arquivo(s) relacionado (s) de sua instalação do Steam.<br /> Excluir loginusers.vdf resultará neste alternador de conta não mostrando contas.<br /> Você precisará fazer login neles usando o Steam para recuperá-los.\n",
  "Cleaning_Button_KillProcess": "Encerrar processo {platform}",
  "Cleaning_Understand": "Eu entendo o que esses botões fazem.",
  "SteamAdvanced_LogPlaceholder": "A saída de cada ação aparecerá aqui.",
  "SteamAdvanced_NoOutput": "(sem saída)",
  "SteamAdvanced_LogError": "Erro: {message}",
  "SteamAdvanced_ClosedSteam": "Steam fechada (ou a Steam não estava em execução).",
  "SteamAdvanced_SkippedFolderMissing": "Ignorado {label}: a pasta não existe ({path}).",
  "SteamAdvanced_ErrorOpening": "Erro ao abrir {label}: {error}",
  "SteamAdvanced_ErrorReading": "Erro ao ler {label}: {error}",
  "SteamAdvanced_SkippedNotDirectory": "Ignorado {label}: não é um diretório.",
  "SteamAdvanced_CouldNotRemove": "Não foi possível remover {path}: {error}",
  "SteamAdvanced_ClearEmpty": "Limpo {label}: nada para remover (já está vazio).",
  "SteamAdvanced_RemovedFiles": "Limpo {label}: {count} arquivo(s) removido(s).",
  "SteamAdvanced_NoFiles": "Limpo {label}: nenhum arquivo encontrado.",
  "SteamAdvanced_Removed": "Removido {label}.",
  "SteamAdvanced_NoSsfnFiles": "Nenhum arquivo SSFN encontrado.",
  "Toast_DataLocationSuccess": "Local dos dados do usuário atualizado com sucesso.",
  "Button_PortableMode": "Modo Portátil",
  "Tooltip_PortableMode": "Pressionar isto irá mover a pasta do TcNo Account Switcher para junto do .exe para instalações portáteis.",
  "Toast_PlaceShortcutFiles": "Uma pasta está abrindo. Coloque os atalhos do jogo nessa pasta e reinicie o alternador de contas.",
  "Toast_Copied": "Copiado",
  "Toast_ProtocolEnabled": "Este programa agora responderá a tcno:\\\\ no Windows",
  "Toast_ProtocolDisabled": "Este programa não responderá mais a tcno:\\\\",
  "Toast_OfflineModeEnabled": "Modo offline ativado: nenhuma solicitação de rede externa do aplicativo.",
  "Toast_OfflineModeDisabled": "Modo offline desativado: a atualização de perfil e API podem usar a rede novamente.",
  "Toast_OfflineModeNoLinks": "Modo offline ativado: abra o link no seu navegador manualmente, se necessário.",
  "Toast_RestartAsAdmin": "Comece como administrador e tente novamente.",
  "Toast_CreateShortcutFailed": "Não foi possível criar o atalho",
  "Toast_ShortcutCreated": "Atalho criado!",
  "Toast_ShortcutImported": "Adicionado(s) {count} atalho(s)",
  "Toast_ShortcutImportUnsupported": "Apenas arquivos .lnk e .url podem ser soltos aqui",
  "Toast_ShortcutImportFailed": "Não foi possível importar o atalho",
  "DropOverlay_CopyShortcut": "Solte para copiar o atalho",
  "Overlay_UserDataMove": "Copiando dados do usuário para o novo local…",
  "Overlay_UserDataMoveRestarting": "Reiniciando para terminar de mover os dados do usuário…",
  "Drop_SetAccountIcon": "Definir ícone",
  "Toast_SettingsCopied": "Configurações copiadas com sucesso para a conta atual.",
  "Toast_GameDataRestored": "Dados de jogo restaurados com sucesso para esta conta.",
  "Toast_NoValidSteamId": "Não foi possível encontrar um Steam ID válido.",
  "Toast_FailedUpdateCheck": "Falha ao verificar se há atualizações",
  "Toast_UpToDate": "Você está atualizado!",
  "Toast_StartedGame": "Iniciado {program}",
  "Toast_Steam_VacCleared": "O status do VAC para contas foi apagado",
  "Toast_NoFindSteamUserdata": "Não foi possível encontrar a pasta Steam\\\\userdata",
  "Toast_NoFindGameBackup": "Não foi possível encontrar a pasta de dados do jogo de backup para esta conta.",
  "Toast_GameBackupDone": "Pasta de dados do jogo copiada com sucesso: {folderLocation}",
  "Toast_SavedItem": "Salvo: {item}",
  "Toast_RestoreComplete": "Restauração concluída!",
  "Toast_PlatformsJsonUpdateFound": "Uma versão mais recente do Platforms.json está disponível (v{version}). Baixando…",
  "Toast_PlatformsJsonUpdated": "Platforms.json atualizado para v{version}.",
  "Toast_FailedStatsLoad": "Falha ao carregar GameStats.json! Verifique se este arquivo existe.",
  "Toast_GameStatsLoadFail": "Falha ao obter estatísticas de jogo da web para {Game}",
  "Toast_UpdateCheckFail": "Não foi possível acessar https://tcno.co/ para verificar se há atualizações. Esta mensagem será exibida uma vez por dia.",
  "Toast_SameAccount": "Não é possível copiar arquivos de/para a mesma conta. Experimente uma conta diferente ou consulte Wiki para obter mais informações.",
  "Toast_FoundExeViaShortcut": "Encontramos o caminho instalado a partir de um atalho do Menu Iniciar. Verifique sua localização clicando em Configurações agora. Clique para descartar.",
  "Modal_Crowdin_Header": "Tradutores Crowdin",
  "Modal_Crowdin_Info": "Aqui estão todos que ajudaram a traduzir este software.<br>Usuários com idiomas próximos a eles ajudaram muito na tradução (função de revisor).",
  "Modal_Info_Creator": "Criado por TroubleChute [Wesley Pyburn]",
  "Modal_Info_Version": "Versão",
  "Modal_Info_ViewGitHub": "Ver no GitHub",
  "Modal_Info_ViewPatreon": "Suporte via Patreon",
  "Modal_Info_ViewKofi": "Suporte via Ko-Fi",
  "Modal_Info_BugReport": "Relatório de erro/solicitação de recurso",
  "Modal_Info_VisitSite": "Visite tcno.co",
  "Modal_Info_Disclaimer": "Isenção de responsabilidade",
  "Modal_Title_Info": "Informações do TcNo Account Switcher",
  "Modal_Title_ConfirmAction": "TcNo Account Switcher Confirmar ação",
  "Modal_Title_LocatePlatform": "Por favor, localize o diretório {platform}",
  "Modal_Title_MoveUserdata": "Selecionar local para mover os dados do usuário",
  "Modal_GameStats_Header": "Habilitar/Desabilitar estatísticas do jogo para: {accountName}",
  "Modal_GameVars_Header": "Insira os seguintes detalhes para sua conta {game}, {username} em {platform}",
  "Modal_Title_AccountNotes": "Notas da conta para: {accountName}",
  "Modal_Title_MissingPlatformsJson": "Platforms.json não encontrado",
  "Modal_Body_MissingPlatformsJson": "O arquivo Platforms.json não foi encontrado na pasta do TcNo Account Switcher ao lado deste programa. Escolha um arquivo para usar ou restaure a lista padrão fornecida com o aplicativo.",
  "Modal_SetBackground": "Selecione uma imagem ou insira um URL abaixo.<br>Deixe em branco e defina para reiniciar.<br>(Para um controle mais avançado, consulte Theming on the Wiki):",
  "Modal_SetBackground_ChooseImage": "Escolha a imagem local",
  "Modal_SetUserdata": "Digite um caminho de pasta abaixo e clique em definir.",
  "Modal_SetUserdata_ChooseFolder": "Selecione uma pasta",
  "Modal_Button_Select": "Selecionar",
  "Modal_SetUserdata_Button": "Definir dados do usuário",
  "Modal_ChangeUsername": "Insira um novo nome de usuário para sua conta",
  "Modal_SetPassword": "Digite uma senha para o TcNo Account Switcher",
  "Modal_LocatePlatform": "Localizar {platformExe}",
  "Modal_ConfirmAction": "Confirmar ação",
  "Modal_CrashReport_Title": "Falha detectada",
  "Modal_CrashReport_Body": "Parece que ocorreu uma falha!\nDeseja enviar seu log de falhas para ajudar a depurar e corrigir problemas?\n\nNota: Este relatório pode incluir nomes de usuário, IDs de conta e outras informações que você inseriu ou que o programa coletou.",
  "Status_SelectedAccount": "Selecionado: {name}",
  "Status_Init": "Status: inicializando",
  "Status_ClosingPlatform": "Fechando {platform}",
  "Status_ClosingPlatformFailed": "Falha ao fechar {platform}",
  "Status_StartingPlatform": "Iniciando {platform}",
  "Toast_UrlAdminErr": "Você não pode executar arquivos .url como administrador. Tente outro tipo de atalho. Iniciando como usuário normal.",
  "Status_UpdatingFile": "Atualizando {file}",
  "Status_UpdatingRegistry": "Atualizando o registro do Windows",
  "Status_FailedLog": "Ação falhou. Veja o log para detalhes.",
  "Status_WaitingForClose": "Aguardando {processName} fechar ({timeout}/{timeLimit} segundos)",
  "Status_WaitingForMultipleClose": "Aguardando {processName} e {count} outros fecharem ({timeout}/{timeLimit} segundos)",
  "Status_GetUniqueId": "Coletando ID de usuário exclusivo",
  "Status_CopyingFiles": "Copiando arquivos do usuário...",
  "Status_HandlingImage": "Manipulando a imagem do perfil da conta",
  "Status_ActionBar_PreparingSave": "Preparando para salvar…",
  "Status_ActionBar_SavingSession": "Salvando sessão atual…",
  "Status_ActionBar_ClearingSession": "Limpando sessão atual…",
  "Status_ActionBar_RestoringAccount": "Restaurando conta salva…",
  "Status_ActionBar_UpdatingSteamLogin": "Atualizando dados de login da Steam…",
  "Status_ActionBar_UpdatingSteamPersona": "Atualizando estado do perfil da Steam…",
  "Tags_Section": "Marcadores",
  "Tags_Add": "Adicionar tags",
  "Tags_Modify": "Modificar tags",
  "Tags_ModifyEmpty": "(nenhum)",
  "Tags_AddExpiry": "Adicionar expiração",
  "Tags_AddExpiryBody": "Escolha quando <b>{tag}</b> deve expirar.",
  "Tags_SaveExpiry": "Definir expiração",
  "Tags_RemoveAll": "Remover todos",
  "Tags_AddSpecial": "Adicionar especial",
  "Tags_ExpiryScope": "Aplicar expiração a",
  "Tags_ExpiryScope_All": "Todos os tags correspondentes",
  "Tags_ExpiryScope_AccountOnly": "Tag apenas para esta conta",
  "Tags_ExpiryDate": "Data",
  "Tags_ExpiryTime": "Hora",
  "Tags_ExpiryCountdown": "Expira em {countdown}",
  "Tags_Remove": "Remover tags",
  "Tags_RemoveEmpty": "(nenhum)",
  "Tags_SearchPlaceholder": "Pesquisar ou criar tag…",
  "Tags_All": "Todas as tags",
  "Tags_Filter_All": "Todos",
  "Tags_Filter_Untagged": "Sem tag",
  "Context_SwapTo": "Trocar para conta",
  "Context_CreateShortcut": "Criar atalho",
  "Context_CreateShortcut_SwapTo": "Criar atalho (& Alternar para {name})",
  "Context_CreateShortcut_SelectAccount": "Criar atalho (Selecione uma conta primeiro)",
  "Context_ChangeImage": "Alterar imagem",
  "Context_ChooseProfileImage": "Escolher imagem",
  "Context_RemoveProfileImage": "Remover imagem",
  "Overlay_ProfileImageTitle": "Definir imagem da conta",
  "Overlay_ProfileImageHint": "Arraste e solte um arquivo de imagem para a conta: {name} ou clique abaixo para selecionar uma.",
  "Overlay_ProfileImageClickToBrowse": "Clique para abrir o seletor de arquivos",
  "Context_ChangeName": "Alterar o nome do mudador",
  "Context_LoginAsSubmenu": "Entrar como",
  "Context_CopySubmenu": "Copiar",
  "Context_CommunityUrl": "URL da comunidade",
  "Context_CommunityUsername": "Nome de usuário da comunidade",
  "Context_LoginUsername": "Nome de usuário de login",
  "Context_CopySteamIdSubmenu": "Copiar SteamID",
  "Context_Steam_Id": "SteamID [STEAM0:~]",
  "Context_Steam_Id3": "SteamID3 [U:1:~]",
  "Context_Steam_Id32": "SteamID32",
  "Context_Steam_Id64": "SteamID64 7656~",
  "Context_Steam_OpenUserdata": "Abrir userdata",
  "Context_ManageSubmenu": "Gerenciar",
  "Context_GameDataSubmenu": "Dados do jogo",
  "Context_GameData_NoFolders": "Nenhum título instalado tem dados locais do jogo ou um backup salvo para esta conta ainda.",
  "Context_ManageGameStats": "Estatísticas do jogo",
  "Context_Game_CopySettingsFrom": "Copiar configurações para o atual",
  "Context_Game_RestoreSettingsTo": "Restaurar dados do jogo",
  "Context_Game_BackupData": "Backup de dados do jogo",
  "Context_HidePlatform": "Ocultar plataforma",
  "Context_RunAdmin": "Executar como administrador",
  "Context_Hide": "Ocultar",
  "Context_Search": "Pesquisar…",
  "Context_Game_LoginAndLaunch": "Alternar e iniciar",
  "Context_CreateTag": "Criar:",
  "Status_Updating": "Atualizando…",
  "Aria_PreviousPage": "Página anterior",
  "Aria_NextPage": "Próxima página",
  "Aria_RepeatedTimes": "Repetido {count} vezes",
  "Aria_DismissNotification": "Descartar notificação",
  "Aria_WindowBack": "Voltar",
  "Aria_WindowMinimize": "Minimizar janela",
  "Aria_WindowMaximize": "Maximizar janela",
  "Aria_WindowRestore": "Restaurar janela",
  "Aria_WindowClose": "Fechar janela",
  "Aria_OpenSettings": "Abrir configurações",
  "Aria_OpenInfo": "Abrir informações",
  "Aria_Expand": "Expandir",
  "Aria_Collapse": "Recolher",
  "Aria_OpenPlatform": "Abrir {platform}",
  "Toast_CopyFailed": "Não foi possível copiar para a área de transferência.",
  "Context_Reorder": "Reordenar",
  "Context_MoveLeft": "Mover para a esquerda",
  "Context_MoveRight": "Mover para a direita",
  "Context_MoveToStart": "Mover para o início",
  "Context_MoveToEnd": "Mover para o fim",
  "Context_Pin": "Fixar",
  "Context_Unpin": "Desafixar",
  "Context_MoveToPinned": "Mover para fixados",
  "Context_MoveToDropdown": "Mover para o menu suspenso",
  "Command_MoveSelectedAccountLeft": "Mover a conta selecionada para a esquerda",
  "Command_MoveSelectedAccountRight": "Mover a conta selecionada para a direita",
  "Command_MoveSelectedAccountStart": "Mover a conta selecionada para o início",
  "Command_MoveSelectedAccountEnd": "Mover a conta selecionada para o fim",
  "Command_MoveShortcutLeft": "Mover atalho para a esquerda: {name}",
  "Command_MoveShortcutRight": "Mover atalho para a direita: {name}",
  "Command_PinShortcut": "Fixar atalho: {name}",
  "Command_UnpinShortcut": "Desafixar atalho: {name}",
  "Command_MoveShortcutToPinned": "Mover atalho para fixados: {name}",
  "Command_MoveShortcutToDropdown": "Mover atalho para o menu suspenso: {name}",
  "Command_MovePlatformLeft": "Mover {platform} para a esquerda",
  "Command_MovePlatformRight": "Mover {platform} para a direita",
  "Command_MovePlatformStart": "Mover {platform} para o início",
  "Command_MovePlatformEnd": "Mover {platform} para o fim",
  "Shortcut_ListPinned": "atalhos fixados",
  "Shortcut_ListDropdown": "menu suspenso",
  "Toast_MovedItemPosition": "{item} movido para a posição {position} de {total}.",
  "Toast_MovedItemToListPosition": "{item} movido para {list}, posição {position} de {total}.",
  "Title_Platforms_Settings": "TcNo Account Switcher - Configurações da plataforma",
  "Title_Settings_TestCss": "TcNo Account Switcher - Testar estilo CSS",
  "Title_AccountsList": "TcNo Account Switcher - {platform}",
  "Title_Settings": "TcNo Account Switcher - Configurações",
  "Title_Steam_Cleaning": "TcNo Account Switcher - Limpeza do Steam",
  "Title_Template_Settings": "TcNo Account Switcher - Configurações de {platformName}",
  "Tray_Switch": "Mudar para: {account}",
  "Tray_Unlock": "Desbloquear",
  "Tray_Exit": "Sair",
  "CLI_Swap": "Alternar",
  "CLI_Logout": "Encerrar sessão",
  "Updater_Checking": "Verificando se há atualizações",
  "Online": "Conectado",
  "Offline": "Desconectado",
  "Invisible": "Invisível",
  "Busy": "Ocupado",
  "Away": "Longe",
  "Snooze": "Pausa",
  "LookingToTrade": "Quer negociar",
  "LookingToPlay": "Quer jogar",
  "Yes": "Sim",
  "No": "Não",
  "Save": "Salvar",
  "NoDefault": "Não (Padrão)",
  "Ok": "OK",
  "Submit": "Submeter",
  "Forget": "Esquecer",
  "Notes": "Observações",
  "Error": "Erro",
  "Failed": "Falhou",
  "Success": "Sucesso",
  "NotFound": "Não Encontrado",
  "Done": "Concluído",
  "Edit": "Editar",
  "Refresh": "Atualizar",
  "Working": "Trabalhando...",
  "ForName": "Para: {name}",
  "Prompt_RestartAsAdmin": "<h3><bold>Este programa será reiniciado como Admin</bold></h3><p>Clique em \"Sim\" no UAC quando solicitado para admin.</p>",
  "Prompt_ForgetAccount": "<h3 style='color:red'>Você está prestes a esquecer uma conta!</h3> <h4>O que isso significa?</h4> <p>O TcNo Account Switcher também deixará de mostrar a conta,<br/> até que ela seja conectada novamente pelo {platform} e adicionada à lista.</p> <p>Sua conta permanecerá intacta. Ela será apenas esquecida neste computador.</p> <h4>Você entende?</h4>\n",
  "Prompt_ClearStats": "<h3 style='color:red'>Você está prestes a limpar suas estatísticas!</h3> <p>Você não pode desfazer esta ação.</p>\n",
  "Platform_ClearCache": "Limpar cache",
  "Tooltip_Settings": "Configurações",
  "Tooltip_Info": "Informações",
  "Tooltip_ManagePlatforms": "Mostrar ou ocultar outras plataformas",
  "Tooltip_ExpandShortcuts": "Expandir a seleção de jogos e atalhos",
  "Tooltip_ShortcutFolder": "Abra a pasta de atalho. Coloque atalhos lá e o TcNo Account Switcher para vê-los.",
  "Tooltip_Backup": "Arquivos/pastas de configuração de backup, conforme definido nas configurações da plataforma.",
  "Tooltip_BackupAll": "Faça backup de TODOS os arquivos/pastas de configuração, incluindo imagens e outros arquivos grandes.",
  "Tooltip_ClosingMethod": "Combinar é o melhor. Fechar tentativas de fechar diretamente através de uma função de fechamento e TaskKill usa CMD (Melhor se combinado não funciona)",
  "Tooltip_StartingMethod": "O padrão é o melhor. O Direct não tem controle sobre o nível de administração ou UAC. Ele começará como o mesmo nível (ou superior - mas não inferior) que este alternador de conta",
  "Tooltip_CurrentAccount": "No momento, você está conectado a esta conta.",
  "Website": "Site",
  "Preview_Platforms": "Pré-visualização de plataformas",
  "Preview_Accounts": "Visualização de contas",
  "Preview_Notifications": "Pré-visualização das notificações de brinde",
  "Preview_Settings": "Visualização de configurações",
  "Preview_Modals": "Visualização de modais",
  "Preview_OverlayDropReceivers": "Sobreposições de soltar arquivo",
  "Settings_PreviewOverlayDropReceivers": "Receptores em tela cheia e dicas por conta exibidos ao arrastar imagens de perfil ou atalhos. As prévias estáticas abaixo correspondem a esses estados.",
  "Preview_AccountDropOnRows": "Linhas de conta (soltar imagem de perfil)",
  "Preview_AccountDropRowNormal": "Linha normal",
  "Preview_AccountDropRowDragHover": "Receptor de soltar (passar mouse sobre a linha)",
  "Toast_CrashReported": "Um relatório de falha foi enviado com sucesso.",
  "Toast_CrashReportSubmitFailed": "Não foi possível enviar o relatório de falhas.",
  "Heading_UpdateAvailable": "Atualização disponível",
  "Button_UpdateNow": "Atualizar agora",
  "Button_CheckForUpdates": "Verificar atualizações",
  "Button_OpenDownloadPage": "Baixar do GitHub",
  "Button_Loading": "Carregando…",
  "Stability_DidSwitchWork": "A alteração funcionou?",
  "Stability_ThanksRating": "Obrigado por avaliar",
  "Stability_ThanksReportLine1": "Obrigado por avaliar.",
  "Stability_ThanksReportAskPrefix": "Precisa",
  "Stability_ThanksReportAskSuffix": "?",
  "Stability_ReportIssue": "relatar um problema",
  "Stability_ThumbUp": "Sim, a alteração funcionou",
  "Stability_ThumbDown": "Não, a alteração não funcionou",
  "Feedback_Issue_Title": "Relatar um problema",
  "Feedback_Issue_Body": "Descreva o que deu errado e o que você esperava:",
  "Feedback_Suggestion_Title": "Sugerir funcionalidade ou alteração",
  "Feedback_Suggestion_Body": "Digite uma ideia, alteração ou correção em detalhes:",
  "Feedback_Submit": "Enviar",
  "Feedback_AttachLog": "Enviar log",
  "Feedback_AttachLog_Hint": "Nomes de usuário, IDs e detalhes semelhantes são removidos do log da melhor forma possível antes do envio.",
  "Feedback_DiscordLink": "Entre no Discord da comunidade",
  "Toast_FeedbackThanks": "Obrigado pelo seu feedback.",
  "Toast_FeedbackSubmitFailed": "Não foi possível enviar o feedback."
}
